flake8_requests/__init__.py
flake8_requests/constants.py
flake8_requests/dont_handle_redirects.py
flake8_requests/main.py
flake8_requests/no_auth_over_http.py
flake8_requests/requests_base_visitor.py
flake8_requests/use_scheme.py
flake8_requests/use_timeout.py
flake8_requests-0.4.0.dist-info/entry_points.txt
flake8_requests-0.4.0.dist-info/WHEEL
flake8_requests-0.4.0.dist-info/METADATA
flake8_requests-0.4.0.dist-info/RECORD
